{
  "id": "elit_19796",
  "title": "Cartucho de Tinta Brother LC406XLYs Amarillo",
  "price": 126720.35,
  "originalPrice": 64.3,
  "discount": null,
  "image": "https://images.elit.com.ar/p/19796/i/069Ok_l.webp",
  "slug": "cartucho-de-tinta-brother-lc406xlys-amarillo",
  "categorySlug": "insumos",
  "category": "Insumos",
  "subcategory": "Cartuchos de Tinta",
  "brand": "BROTHER",
  "sku": "LC406XLYS",
  "ean": "0",
  "warranty": "12",
  "description": "Cartucho de Tinta Brother LC406XLYs Amarillo - 12",
  "rating": 0,
  "reviewsCount": 0,
  "freeShipping": false,
  "installments": {
    "count": 6,
    "value": 21120
  },
  "stock": 4,
  "provider": "elit",
  "providerStore": "minorista",
  "isGamer": false,
  "dollarRate": 1450.0
}