{
  "id": "elit_19259",
  "title": "Tarjeta de Memoria Sandisk MicroSDXC 128GB UHS-I Card C10 U3 100Mb for Nintendo Switch Fortnite Edition",
  "price": 66730.19,
  "originalPrice": 33.86,
  "discount": null,
  "image": "https://images.elit.com.ar/p/19259/i/hAGIm_l.webp",
  "slug": "tarjeta-de-memoria-sandisk-microsdxc-128gb-uhs-i-card-c10-u3-100mb-for-nintendo-switch-fortnite-edition",
  "categorySlug": "almacenamiento",
  "category": "Almacenamiento",
  "subcategory": "Memorias Flash",
  "brand": "SANDISK",
  "sku": "SDSQXAO-128G-GN6ZG",
  "ean": "619659199739",
  "warranty": "12",
  "description": "Tarjeta de Memoria Sandisk MicroSDXC 128GB UHS-I Card C10 U3 100Mb for Nintendo Switch Fortnite Edition - 12",
  "rating": 0,
  "reviewsCount": 0,
  "freeShipping": false,
  "installments": {
    "count": 6,
    "value": 11122
  },
  "stock": 45,
  "provider": "elit",
  "providerStore": "minorista",
  "isGamer": false,
  "dollarRate": 1450.0
}